AUTHORS
CHANGELOG
LICENSE
MANIFEST.in
README.markdown
astack.py
setup.py
astack.egg-info/PKG-INFO
astack.egg-info/SOURCES.txt
astack.egg-info/dependency_links.txt
astack.egg-info/entry_points.txt
astack.egg-info/top_level.txt