Metadata-Version: 1.1
Name: astack
Version: 0.0.4
Summary: Simple stacktrace analysis tool for the JVM
Home-page: https://github.com/HubSpot/astack/
Author: Michael Axiak
Author-email: mike@axiak.net
License: Copyright (c) 2012 HubSpot, Inc.
